webdriver_setup/__init__.py
webdriver_setup/chrome.py
webdriver_setup/driver.py
webdriver_setup/firefox.py
webdriver_setup/get_webdriver.py
webdriver_setup/opera.py
webdriver_setup/safari.py
webdriver_setup/windows.py
webdriver_setup-1.1.0.dist-info/LICENSE
webdriver_setup-1.1.0.dist-info/METADATA
webdriver_setup-1.1.0.dist-info/WHEEL
webdriver_setup-1.1.0.dist-info/top_level.txt
webdriver_setup-1.1.0.dist-info/RECORD
