Metadata-Version: 2.1
Name: webdriver-setup
Version: 1.1.0
Summary: Easy to use webdriver instance creation api
Home-page: https://github.com/coskundeniz/webdriver-setup
Author: Coşkun Deniz
Author-email: coskun.denize@gmail.com
License: UNKNOWN
Keywords: webdriver,selenium,browser automation,testing,test automation
Platform: UNKNOWN
Classifier: License :: OSI Approved :: Apache Software License
Classifier: Intended Audience :: Information Technology
Classifier: Intended Audience :: Developers
Classifier: Programming Language :: Python :: 3.6
Classifier: Programming Language :: Python :: 3.7
Classifier: Programming Language :: Python :: 3.8
Classifier: Programming Language :: Python :: 3.9
Classifier: Topic :: Software Development :: Libraries
Classifier: Topic :: Software Development :: Testing
Classifier: Topic :: Utilities
Classifier: Operating System :: POSIX
Classifier: Operating System :: Unix
Classifier: Operating System :: MacOS
Classifier: Operating System :: Microsoft :: Windows
Requires-Python: >=3.6
